[
  {
    "udt_error_enum_v0": {
      "doc": "",
      "lib": "",
      "name": "Error",
      "cases": [
        {
          "doc": "",
          "name": "Unauthorized",
          "value": 0
        },
        {
          "doc": "",
          "name": "DepositPending",
          "value": 1
        },
        {
          "doc": "",
          "name": "InvalidToken",
          "value": 2
        },
        {
          "doc": "",
          "name": "Usdm0BeneficiaryNotAssigned",
          "value": 3
        },
        {
          "doc": "",
          "name": "Usdm1BeneficiaryNotAssigned",
          "value": 4
        },
        {
          "doc": "",
          "name": "CollateralNotSupported",
          "value": 5
        },
        {
          "doc": "",
          "name": "NoCollateralsConfigured",
          "value": 6
        },
        {
          "doc": "",
          "name": "DepositAmountInvalid",
          "value": 7
        },
        {
          "doc": "",
          "name": "InsufficientCollateralBalance",
          "value": 8
        },
        {
          "doc": "",
          "name": "InsufficientCollateralAllowance",
          "value": 9
        },
        {
          "doc": "",
          "name": "DepositNotFound",
          "value": 10
        },
        {
          "doc": "",
          "name": "DepositDoesNotMatch",
          "value": 11
        },
        {
          "doc": "",
          "name": "RedemptionPending",
          "value": 12
        },
        {
          "doc": "",
          "name": "RedemptionAmountInvalid",
          "value": 13
        },
        {
          "doc": "",
          "name": "Usdm0NotSet",
          "value": 14
        },
        {
          "doc": "",
          "name": "Usdm1NotSet",
          "value": 15
        },
        {
          "doc": "",
          "name": "InsufficientTokenBalance",
          "value": 16
        },
        {
          "doc": "",
          "name": "InsufficientTokenAllowance",
          "value": 17
        },
        {
          "doc": "",
          "name": "RedemptionNotFound",
          "value": 18
        },
        {
          "doc": "",
          "name": "RedemptionDoesNotMatch",
          "value": 19
        },
        {
          "doc": "",
          "name": "RedemptionNotApproved",
          "value": 20
        },
        {
          "doc": "",
          "name": "ApprovalExceedsDeposit",
          "value": 21
        },
        {
          "doc": "",
          "name": "Paused",
          "value": 22
        },
        {
          "doc": "",
          "name": "SwapAmountInvalid",
          "value": 23
        },
        {
          "doc": "",
          "name": "SwapPending",
          "value": 24
        },
        {
          "doc": "",
          "name": "SwapNotFound",
          "value": 25
        },
        {
          "doc": "",
          "name": "SwapDoesNotMatch",
          "value": 26
        },
        {
          "doc": "",
          "name": "RedemptionAlreadyApproved",
          "value": 27
        },
        {
          "doc": "",
          "name": "AmountExceedsCurrentAmount",
          "value": 28
        },
        {
          "doc": "",
          "name": "ObligationExceedsCurrentObligation",
          "value": 29
        }
      ]
    }
  },
  {
    "udt_union_v0": {
      "doc": "",
      "lib": "",
      "name": "DataKey",
      "cases": [
        {
          "void_v0": {
            "doc": "",
            "name": "Admin"
          }
        },
        {
          "void_v0": {
            "doc": "",
            "name": "Operator"
          }
        },
        {
          "void_v0": {
            "doc": "",
            "name": "Financiers"
          }
        },
        {
          "void_v0": {
            "doc": "",
            "name": "USDM0"
          }
        },
        {
          "void_v0": {
            "doc": "",
            "name": "USDM1"
          }
        },
        {
          "void_v0": {
            "doc": "",
            "name": "Beneficiary0"
          }
        },
        {
          "void_v0": {
            "doc": "",
            "name": "Beneficiary1"
          }
        },
        {
          "void_v0": {
            "doc": "",
            "name": "Collaterals"
          }
        },
        {
          "tuple_v0": {
            "doc": "",
            "name": "Deposit",
            "type_": [
              "address"
            ]
          }
        },
        {
          "tuple_v0": {
            "doc": "",
            "name": "Redemption",
            "type_": [
              "address"
            ]
          }
        },
        {
          "tuple_v0": {
            "doc": "",
            "name": "PendingDeposit",
            "type_": [
              "address"
            ]
          }
        },
        {
          "tuple_v0": {
            "doc": "",
            "name": "Obligation",
            "type_": [
              "address"
            ]
          }
        },
        {
          "void_v0": {
            "doc": "",
            "name": "Paused"
          }
        },
        {
          "tuple_v0": {
            "doc": "",
            "name": "Swap",
            "type_": [
              "address"
            ]
          }
        }
      ]
    }
  },
  {
    "udt_struct_v0": {
      "doc": "",
      "lib": "",
      "name": "Deposit",
      "fields": [
        {
          "doc": "",
          "name": "amount",
          "type_": "i128"
        },
        {
          "doc": "",
          "name": "collateral",
          "type_": "address"
        },
        {
          "doc": "",
          "name": "depositor",
          "type_": "address"
        },
        {
          "doc": "",
          "name": "token_id",
          "type_": "u32"
        }
      ]
    }
  },
  {
    "udt_struct_v0": {
      "doc": "",
      "lib": "",
      "name": "Redemption",
      "fields": [
        {
          "doc": "",
          "name": "amount",
          "type_": "i128"
        },
        {
          "doc": "",
          "name": "amount_approved",
          "type_": "i128"
        },
        {
          "doc": "",
          "name": "collateral",
          "type_": "address"
        },
        {
          "doc": "",
          "name": "redeemer",
          "type_": "address"
        },
        {
          "doc": "",
          "name": "token_id",
          "type_": "u32"
        }
      ]
    }
  },
  {
    "udt_struct_v0": {
      "doc": "",
      "lib": "",
      "name": "Swap",
      "fields": [
        {
          "doc": "",
          "name": "amount",
          "type_": "i128"
        },
        {
          "doc": "",
          "name": "amount_approved",
          "type_": "i128"
        },
        {
          "doc": "",
          "name": "input_token_id",
          "type_": "u32"
        },
        {
          "doc": "",
          "name": "output_token_id",
          "type_": "u32"
        },
        {
          "doc": "",
          "name": "swapper",
          "type_": "address"
        }
      ]
    }
  },
  {
    "udt_struct_v0": {
      "doc": "",
      "lib": "",
      "name": "Config",
      "fields": [
        {
          "doc": "",
          "name": "admin",
          "type_": "address"
        },
        {
          "doc": "",
          "name": "beneficiary0",
          "type_": {
            "option": {
              "value_type": "address"
            }
          }
        },
        {
          "doc": "",
          "name": "beneficiary1",
          "type_": {
            "option": {
              "value_type": "address"
            }
          }
        },
        {
          "doc": "",
          "name": "collaterals",
          "type_": {
            "vec": {
              "element_type": "address"
            }
          }
        },
        {
          "doc": "",
          "name": "operator",
          "type_": {
            "option": {
              "value_type": "address"
            }
          }
        },
        {
          "doc": "",
          "name": "paused",
          "type_": "bool"
        },
        {
          "doc": "",
          "name": "usdm0",
          "type_": {
            "option": {
              "value_type": "address"
            }
          }
        },
        {
          "doc": "",
          "name": "usdm1",
          "type_": {
            "option": {
              "value_type": "address"
            }
          }
        }
      ]
    }
  },
  {
    "function_v0": {
      "doc": "",
      "name": "__constructor",
      "inputs": [
        {
          "doc": "",
          "name": "admin",
          "type_": "address"
        }
      ],
      "outputs": []
    }
  },
  {
    "function_v0": {
      "doc": "",
      "name": "get_administrator",
      "inputs": [],
      "outputs": [
        "address"
      ]
    }
  },
  {
    "function_v0": {
      "doc": "",
      "name": "rotate_administrator",
      "inputs": [
        {
          "doc": "",
          "name": "current_admin",
          "type_": "address"
        },
        {
          "doc": "",
          "name": "new_admin",
          "type_": "address"
        }
      ],
      "outputs": []
    }
  },
  {
    "function_v0": {
      "doc": "",
      "name": "assign_operator",
      "inputs": [
        {
          "doc": "",
          "name": "admin",
          "type_": "address"
        },
        {
          "doc": "",
          "name": "operator",
          "type_": "address"
        }
      ],
      "outputs": []
    }
  },
  {
    "function_v0": {
      "doc": "",
      "name": "get_operator",
      "inputs": [],
      "outputs": [
        {
          "option": {
            "value_type": "address"
          }
        }
      ]
    }
  },
  {
    "function_v0": {
      "doc": "",
      "name": "add_financier",
      "inputs": [
        {
          "doc": "",
          "name": "admin",
          "type_": "address"
        },
        {
          "doc": "",
          "name": "financier",
          "type_": "address"
        }
      ],
      "outputs": []
    }
  },
  {
    "function_v0": {
      "doc": "",
      "name": "get_financiers",
      "inputs": [],
      "outputs": [
        {
          "option": {
            "value_type": {
              "map": {
                "key_type": "address",
                "value_type": "bool"
              }
            }
          }
        }
      ]
    }
  },
  {
    "function_v0": {
      "doc": "",
      "name": "remove_financier",
      "inputs": [
        {
          "doc": "",
          "name": "admin",
          "type_": "address"
        },
        {
          "doc": "",
          "name": "financier",
          "type_": "address"
        }
      ],
      "outputs": []
    }
  },
  {
    "function_v0": {
      "doc": "",
      "name": "assign_usdm0",
      "inputs": [
        {
          "doc": "",
          "name": "admin",
          "type_": "address"
        },
        {
          "doc": "",
          "name": "usdm0",
          "type_": "address"
        }
      ],
      "outputs": []
    }
  },
  {
    "function_v0": {
      "doc": "",
      "name": "get_usdm0",
      "inputs": [],
      "outputs": [
        {
          "option": {
            "value_type": "address"
          }
        }
      ]
    }
  },
  {
    "function_v0": {
      "doc": "",
      "name": "assign_usdm1",
      "inputs": [
        {
          "doc": "",
          "name": "admin",
          "type_": "address"
        },
        {
          "doc": "",
          "name": "usdm1",
          "type_": "address"
        }
      ],
      "outputs": []
    }
  },
  {
    "function_v0": {
      "doc": "",
      "name": "get_usdm1",
      "inputs": [],
      "outputs": [
        {
          "option": {
            "value_type": "address"
          }
        }
      ]
    }
  },
  {
    "function_v0": {
      "doc": "",
      "name": "assign_beneficiary0",
      "inputs": [
        {
          "doc": "",
          "name": "admin",
          "type_": "address"
        },
        {
          "doc": "",
          "name": "beneficiary0",
          "type_": "address"
        }
      ],
      "outputs": []
    }
  },
  {
    "function_v0": {
      "doc": "",
      "name": "get_beneficiary0",
      "inputs": [],
      "outputs": [
        {
          "option": {
            "value_type": "address"
          }
        }
      ]
    }
  },
  {
    "function_v0": {
      "doc": "",
      "name": "assign_beneficiary1",
      "inputs": [
        {
          "doc": "",
          "name": "admin",
          "type_": "address"
        },
        {
          "doc": "",
          "name": "beneficiary1",
          "type_": "address"
        }
      ],
      "outputs": []
    }
  },
  {
    "function_v0": {
      "doc": "",
      "name": "get_beneficiary1",
      "inputs": [],
      "outputs": [
        {
          "option": {
            "value_type": "address"
          }
        }
      ]
    }
  },
  {
    "function_v0": {
      "doc": "",
      "name": "add_collateral",
      "inputs": [
        {
          "doc": "",
          "name": "admin",
          "type_": "address"
        },
        {
          "doc": "",
          "name": "collateral",
          "type_": "address"
        }
      ],
      "outputs": []
    }
  },
  {
    "function_v0": {
      "doc": "",
      "name": "get_collaterals",
      "inputs": [],
      "outputs": [
        {
          "option": {
            "value_type": {
              "map": {
                "key_type": "address",
                "value_type": "bool"
              }
            }
          }
        }
      ]
    }
  },
  {
    "function_v0": {
      "doc": "",
      "name": "remove_collateral",
      "inputs": [
        {
          "doc": "",
          "name": "admin",
          "type_": "address"
        },
        {
          "doc": "",
          "name": "collateral",
          "type_": "address"
        }
      ],
      "outputs": []
    }
  },
  {
    "function_v0": {
      "doc": "",
      "name": "pause",
      "inputs": [
        {
          "doc": "",
          "name": "admin",
          "type_": "address"
        }
      ],
      "outputs": []
    }
  },
  {
    "function_v0": {
      "doc": "",
      "name": "unpause",
      "inputs": [
        {
          "doc": "",
          "name": "admin",
          "type_": "address"
        }
      ],
      "outputs": []
    }
  },
  {
    "function_v0": {
      "doc": "",
      "name": "is_paused",
      "inputs": [],
      "outputs": [
        "bool"
      ]
    }
  },
  {
    "function_v0": {
      "doc": "",
      "name": "get_config",
      "inputs": [],
      "outputs": [
        {
          "udt": {
            "name": "Config"
          }
        }
      ]
    }
  },
  {
    "function_v0": {
      "doc": "",
      "name": "deposit",
      "inputs": [
        {
          "doc": "",
          "name": "depositor",
          "type_": "address"
        },
        {
          "doc": "",
          "name": "collateral",
          "type_": "address"
        },
        {
          "doc": "",
          "name": "amount",
          "type_": "i128"
        },
        {
          "doc": "",
          "name": "token_id",
          "type_": "u32"
        }
      ],
      "outputs": []
    }
  },
  {
    "function_v0": {
      "doc": "",
      "name": "cancel_deposit",
      "inputs": [
        {
          "doc": "",
          "name": "user",
          "type_": "address"
        },
        {
          "doc": "",
          "name": "depositor",
          "type_": "address"
        }
      ],
      "outputs": []
    }
  },
  {
    "function_v0": {
      "doc": "",
      "name": "process_deposit",
      "inputs": [
        {
          "doc": "",
          "name": "user",
          "type_": "address"
        },
        {
          "doc": "",
          "name": "depositor",
          "type_": "address"
        },
        {
          "doc": "",
          "name": "token_id",
          "type_": "u32"
        },
        {
          "doc": "",
          "name": "amount",
          "type_": "i128"
        },
        {
          "doc": "",
          "name": "collateral",
          "type_": "address"
        },
        {
          "doc": "",
          "name": "amount_approved",
          "type_": "i128"
        }
      ],
      "outputs": []
    }
  },
  {
    "function_v0": {
      "doc": "",
      "name": "get_deposit",
      "inputs": [
        {
          "doc": "",
          "name": "depositor",
          "type_": "address"
        }
      ],
      "outputs": [
        {
          "option": {
            "value_type": {
              "udt": {
                "name": "Deposit"
              }
            }
          }
        }
      ]
    }
  },
  {
    "function_v0": {
      "doc": "",
      "name": "get_pending_deposit",
      "inputs": [
        {
          "doc": "",
          "name": "collateral",
          "type_": "address"
        }
      ],
      "outputs": [
        {
          "option": {
            "value_type": "i128"
          }
        }
      ]
    }
  },
  {
    "function_v0": {
      "doc": "",
      "name": "redeem",
      "inputs": [
        {
          "doc": "",
          "name": "redeemer",
          "type_": "address"
        },
        {
          "doc": "",
          "name": "collateral",
          "type_": "address"
        },
        {
          "doc": "",
          "name": "amount",
          "type_": "i128"
        },
        {
          "doc": "",
          "name": "token_id",
          "type_": "u32"
        }
      ],
      "outputs": []
    }
  },
  {
    "function_v0": {
      "doc": "",
      "name": "cancel_redemption",
      "inputs": [
        {
          "doc": "",
          "name": "user",
          "type_": "address"
        },
        {
          "doc": "",
          "name": "redeemer",
          "type_": "address"
        }
      ],
      "outputs": []
    }
  },
  {
    "function_v0": {
      "doc": "",
      "name": "get_redemption",
      "inputs": [
        {
          "doc": "",
          "name": "redeemer",
          "type_": "address"
        }
      ],
      "outputs": [
        {
          "option": {
            "value_type": {
              "udt": {
                "name": "Redemption"
              }
            }
          }
        }
      ]
    }
  },
  {
    "function_v0": {
      "doc": "",
      "name": "approve_redemption",
      "inputs": [
        {
          "doc": "",
          "name": "operator",
          "type_": "address"
        },
        {
          "doc": "",
          "name": "redeemer",
          "type_": "address"
        },
        {
          "doc": "",
          "name": "token_id",
          "type_": "u32"
        },
        {
          "doc": "",
          "name": "amount",
          "type_": "i128"
        },
        {
          "doc": "",
          "name": "collateral",
          "type_": "address"
        },
        {
          "doc": "",
          "name": "amount_approved",
          "type_": "i128"
        }
      ],
      "outputs": []
    }
  },
  {
    "function_v0": {
      "doc": "",
      "name": "process_redemption",
      "inputs": [
        {
          "doc": "",
          "name": "user",
          "type_": "address"
        },
        {
          "doc": "",
          "name": "redeemer",
          "type_": "address"
        }
      ],
      "outputs": []
    }
  },
  {
    "function_v0": {
      "doc": "",
      "name": "get_collateral_obligation",
      "inputs": [
        {
          "doc": "",
          "name": "collateral",
          "type_": "address"
        }
      ],
      "outputs": [
        {
          "option": {
            "value_type": "i128"
          }
        }
      ]
    }
  },
  {
    "function_v0": {
      "doc": "",
      "name": "swap",
      "inputs": [
        {
          "doc": "",
          "name": "swapper",
          "type_": "address"
        },
        {
          "doc": "",
          "name": "input_token_id",
          "type_": "u32"
        },
        {
          "doc": "",
          "name": "amount",
          "type_": "i128"
        }
      ],
      "outputs": []
    }
  },
  {
    "function_v0": {
      "doc": "",
      "name": "cancel_swap",
      "inputs": [
        {
          "doc": "",
          "name": "user",
          "type_": "address"
        },
        {
          "doc": "",
          "name": "swapper",
          "type_": "address"
        }
      ],
      "outputs": []
    }
  },
  {
    "function_v0": {
      "doc": "",
      "name": "process_swap",
      "inputs": [
        {
          "doc": "",
          "name": "user",
          "type_": "address"
        },
        {
          "doc": "",
          "name": "swapper",
          "type_": "address"
        },
        {
          "doc": "",
          "name": "input_token_id",
          "type_": "u32"
        },
        {
          "doc": "",
          "name": "amount",
          "type_": "i128"
        },
        {
          "doc": "",
          "name": "output_token_id",
          "type_": "u32"
        },
        {
          "doc": "",
          "name": "amount_approved",
          "type_": "i128"
        }
      ],
      "outputs": []
    }
  },
  {
    "function_v0": {
      "doc": "",
      "name": "get_swap",
      "inputs": [
        {
          "doc": "",
          "name": "swapper",
          "type_": "address"
        }
      ],
      "outputs": [
        {
          "option": {
            "value_type": {
              "udt": {
                "name": "Swap"
              }
            }
          }
        }
      ]
    }
  }
]